epic7_bot/cli.py
epic7_bot/commands/Arena.py
epic7_bot/commands/Command.py
epic7_bot/commands/Daily.py
epic7_bot/commands/Hunt.py
epic7_bot/commands/Shop.py
epic7_bot/core/DeviceManager.py
epic7_bot/core/Logger.py
epic7_bot/core/MathUtils.py
epic7_bot/core/ScreenManager.py
epic7_bot/core/__init__.py
epic7_bot/images/connecting.png
epic7_bot/images/dispatch_mission.png
epic7_bot/images/dispatch_mission_completed.png
epic7_bot/images/skip_button.png
epic7_bot/images/there_was_a_connection_error.png
epic7_bot/images/hunt/confirm.png
epic7_bot/images/hunt/insufficient_energy.png
epic7_bot/images/hunt/pet_auto_battle_active.png
epic7_bot/images/hunt/repeat_battling_has_ended.png
epic7_bot/images/hunt/stage_clear.png
epic7_bot/images/hunt/try_again.png
epic7_bot/images/secret_shop/Buy_button.png
epic7_bot/images/secret_shop/covenant.png
epic7_bot/images/secret_shop/mystic.png
epic7_bot/modules/Arena.py
epic7_bot/modules/Battle.py
epic7_bot/modules/Guild.py
epic7_bot/modules/Module.py
epic7_bot/modules/PetHouse.py
epic7_bot/modules/Sanctuary.py
epic7_bot/modules/SecretShop.py
epic7_bot/modules/Summon.py
epic7_bot/modules/__init__.py
epic7_bot/processes/CheckConnection.py
epic7_bot/processes/CommandRunner.py
epic7_bot/processes/DispatchMissionChecker.py
epic7_bot/processes/__init__.py
epic7_bot/templates/BaseTemplates.py
epic7_bot/templates/CommonTemplates.py
epic7_bot/templates/HuntTemplates.py
epic7_bot/templates/SecretShopTemplates.py
epic7_bot/templates/Template.py
epic7_bot/templates/__init__.py
epic7_bot/utils/Singleton.py
epic7_bot/utils/Spinner.py
epic7_bot/utils/__init__.py
epic7_bot/utils/runInParallel.py
epic7_bot-1.0.3.dist-info/LICENSE
epic7_bot-1.0.3.dist-info/METADATA
epic7_bot-1.0.3.dist-info/WHEEL
epic7_bot-1.0.3.dist-info/entry_points.txt
epic7_bot-1.0.3.dist-info/top_level.txt
epic7_bot-1.0.3.dist-info/RECORD
