Metadata-Version: 2.1
Name: epic7-bot
Version: 1.0.3
Summary: Epic7 Bot used via cli
Author: brunocordioli072
License-File: LICENSE
Requires-Dist: numpy ==1.23.2
Requires-Dist: opencv-python ==4.6.0.66
Requires-Dist: pure-python-adb ==0.3.0.dev0
Requires-Dist: docopt ==0.6.2
Requires-Dist: python-dotenv ==0.21.0
Requires-Dist: psutil ==5.9.3
